{
    "main": {
        "links": [
            {
                "name": "Angular",
                "route_name": "docs.angular.angular-cheatsheet",
                "icon": "angular",
                "exclude_route": true
            },
            {
                "name": "AlpineJS",
                "route_name": "docs.alpine.alpine-cheatsheet",
                "icon": "alpinejs",
                "exclude_route": true
            },
            {
                "name": "CSS",
                "route_name": "docs.css.css-cheatsheet",
                "icon": "css",
                "exclude_route": true
            },
            {
                "name": "ExpressJS",
                "route_name": "docs.expressjs-cheatsheet",
                "icon": "expressjs"
            },
            {
                "name": "Github",
                "route_name": "docs.github-cheatsheet",
                "icon": "github"
            },
            {
                "name": "Google Maps",
                "route_name": "docs.google-maps",
                "icon": "googlemaps"
            },
            {
                "name": "Ionic",
                "route_name": "docs.ionic.ionic-cheatsheet",
                "icon": "ionic",
                "exclude_route": true
            },
            {
                "name": "JavaScript",
                "route_name": "docs.javascript.javascript-fundamentals-quick-reference",
                "icon": "javascript",
                "exclude_route": true
            },
            {
                "name": "Laravel",
                "route_name": "docs.laravel.quick-reference",
                "icon": "laravel",
                "exclude_route": true
            },
            {
                "name": "Linux",
                "route_name": "docs.linux.linux-cheatsheet",
                "icon": "linux",
                "exclude_route": true
            },
            {
                "name": "Livewire",
                "route_name": "docs.livewire.quick-reference",
                "icon": "livewire",
                "exclude_route": true
            },
            {
                "name": "MongoDB",
                "route_name": "docs.mongo-cheatsheet",
                "icon": "mongodb"
            },
            {
                "name": "Mermaid",
                "route_name": "docs.mermaid-cheatsheet",
                "icon": "mermaidjs"
            },
            {
                "name": "NPM",
                "route_name": "docs.npm-cheatsheet",
                "icon": "npm"
            },
            {
                "name": "Pest",
                "route_name": "docs.laravel.testing",
                "icon": "pest",
                "exclude_route": true
            },
            {
                "name": "PHP",
                "route_name": "docs.php.php-cheatsheet",
                "icon": "php",
                "exclude_route": true
            },
            {
                "name": "React",
                "route_name": "docs.react-cheatsheet",
                "icon": "react",
                "exclude_route": true
            },
            {
                "name": "React Native",
                "route_name": "docs.react.react-native-quick-reference",
                "icon": "react",
                "exclude_route": true
            },
            {
                "name": "Redux",
                "route_name": "docs.redux-overview",
                "icon": "redux"
            },
            {
                "name": "Regex",
                "route_name": "docs.regex-cheatsheet",
                "icon": "regex"
            },

            {
                "name": "Socket.IO",
                "route_name": "docs.socket-cheatsheet",
                "icon": "socketio"
            },
 
            {
                "name": "TypeDoc",
                "route_name": "typedoc.typedoc-cheatsheet",
                "view": "pages.typedoc-cheatsheet",
                "icon": "typedoc"
            },
            {
                "name": "Typescript",
                "route_name": "typescript.typescript-cheatsheet",
                "view": "pages.typescript-cheatsheet",
                "icon": "typescript"
            },
            {
                "name": "ViteJS",
                "route_name": "docs.vite-cheatsheet",
                "icon": "vitejs"
            },
            {
                "name": "XAMPP",
                "route_name": "docs.xampp-cheatsheet",
                "icon": "xampp"
            }
        ]
    },
    "other": {
        "links": [
            {
                "name": "Google Maps",
                "route_name": "docs.google-maps"
            },
            {
                "name": "ChoicesJS",
                "route_name": "docs.choices_js"
            }
        ]
    },
    "php": {
        "standalone_menu": true,
        "include_menus": [
            "main"
        ],
        "links": [
            {
                "name": "Cheatsheet",
                "route_name": "docs.php.php-cheatsheet",
                "icon": "php"
            },
            {
                "name": "Array",
                "route_name": "docs.php.array",
                "icon": "php"
            },
            {
                "name": "Conditionals",
                "route_name": "docs.php.conditionals",
                "icon": "php"
            },
            {
                "name": "Enums",
                "route_name": "docs.php.enums",
                "icon": "php"
            }
        ]
    }
}